{
  "navBar.home": { "en": "Home", "fr": "Accueil", "es": "Inicio" },
  "navBar.settings": { "en": "Settings", "fr": "Paramètres", "es": "Ajustes" },

  "sort.categories.title": { "en": "Sort categories", "fr": "Trier les catégories", "es": "Ordenar categorías" },
  
  "common.add": { "en": "Add", "fr": "Ajouter", "es": "Añadir" },
  "common.ok": { "en": "OK", "fr": "OK", "es": "OK" },
  "common.edit": { "en": "Edit", "fr": "Modifier", "es": "Editar" },
  "common.delete": { "en": "Delete", "fr": "Supprimer", "es": "Eliminar" },
  "common.cancel": { "en": "Cancel", "fr": "Annuler", "es": "Cancelar" },
  "common.enabled": { "en": "Enabled", "fr": "Activée", "es": "Activada" },
  "common.disabled": { "en": "Disabled", "fr": "Désactivée", "es": "Desactivada" },
  "common.import": { "en": "Import", "fr": "Importer", "es": "Importar" },
  "common.export": { "en": "Export", "fr": "Exporter", "es": "Exportar" },

  "app.title": { "en": "My Vault", "fr": "Mon Coffre", "es": "Mi Bóveda" },
  "fab.addPassword": { "en": "Add password", "fr": "Ajouter un mot de passe", "es": "Añadir contraseña" },

  "home.empty": { "en": "No passwords yet", "fr": "Aucun mot de passe pour le moment", "es": "Aún no hay contraseñas" },

  "settings.pageTitle": { "en": "Settings", "fr": "Paramètres", "es": "Ajustes" },
  "settings.language": { "en": "Language", "fr": "Langue", "es": "Idioma" },
  "settings.importExport.title": { "en": "Import / Export", "fr": "Export / Import", "es": "Exportar / Importar" },
  "settings.importExport.selectCategory": { "en": "Select a category", "fr": "Sélectionner une catégorie", "es": "Seleccionar una categoría" },
  "settings.importExport.uncategorized": { "en": "Uncategorized", "fr": "Sans catégorie", "es": "Sin categoría" },

  "settings.security.title": { "en": "Security", "fr": "Sécurité", "es": "Seguridad" },
  "settings.security.question": { "en": "Secret question", "fr": "Question secrète", "es": "Pregunta secreta" },
  "settings.security.questionDesc": { "en": "Enable a question to recover access", "fr": "Activer une question pour récupérer l'accès", "es": "Activar una pregunta para recuperar el acceso" },
  "settings.security.questionDisableTitle": { "en": "Disable secret question", "fr": "Désactiver la question secrète", "es": "Desactivar pregunta secreta" },
  "settings.security.fingerprint": { "en": "Fingerprint / Face ID", "fr": "Empreinte / Face ID", "es": "Huella / Face ID" },
  "settings.security.fingerprintDesc": { "en": "Use biometric authentication if available", "fr": "Utiliser la biométrie si disponible", "es": "Usar autenticación biométrica si está disponible" },
  "settings.security.lockTimeout": { "en": "Lock after (minutes)", "fr": "Verrouiller après (minutes)", "es": "Bloquear después (minutos)" },
  "settings.security.oldPassword.title": { "en": "Old password marker", "fr": "Marqueur vieux mot de passe", "es": "Marcador de contraseña antigua" },
  "settings.security.oldPassword.desc": {
    "en": "Mark passwords that are older than the configured threshold.",
    "fr": "Marquer les mots de passe plus anciens que le seuil configuré.",
    "es": "Marcar contraseñas más antiguas que el umbral configurado."
  },
  "settings.security.oldPassword.placeholder": { "en": "Threshold", "fr": "Seuil", "es": "Umbral" },
  "settings.security.oldPassword.unit.days": { "en": "Days", "fr": "Jours", "es": "Días" },
  "settings.security.oldPassword.unit.months": { "en": "Months", "fr": "Mois", "es": "Meses" },
  "settings.security.oldPassword.unit.years": { "en": "Years", "fr": "Années", "es": "Años" },

  "question.label": { "en": "Question", "fr": "Question", "es": "Pregunta" },
  "question.selectPlaceholder": { "en": "Choose a question", "fr": "Choisir une question", "es": "Elegir una pregunta" },
  "question.hint.label": { "en": "Hint (optional)", "fr": "Indice (optionnel)", "es": "Pista (opcional)" },
  "question.hint.save": { "en": "Save hint", "fr": "Enregistrer l'indice", "es": "Guardar pista" },
  "question.answer.label": { "en": "Answer (secure)", "fr": "Réponse (saisie sécurisée)", "es": "Respuesta (segura)" },
  "question.answer.save": { "en": "Save answer", "fr": "Enregistrer la réponse", "es": "Guardar respuesta" },
  "question.confirmSave": { "en": "Confirm save", "fr": "Confirmer la réponse", "es": "Confirmar guardado" },
  "question.confirmOverwrite": { "en": "A saved answer already exists. Do you want to overwrite it?", "fr": "Une réponse est déjà enregistrée. Confirmez-vous l'écrasement de l'ancienne réponse ?", "es": "Ya existe una respuesta guardada. ¿Deseas sobrescribirla?" },
  "question.disable.confirm": { "en": "Disable secret question and remove stored hint/answer?", "fr": "Voulez-vous supprimer la question et la réponse enregistrées ?", "es": "¿Desea eliminar la pregunta y la respuesta guardadas?" },

  "modal.addPassword.title": { "en": "Add password", "fr": "Ajouter un mot de passe", "es": "Añadir contraseña" },
  "modal.editPassword.title": { "en": "Edit password", "fr": "Modifier le mot de passe", "es": "Editar contraseña" },
  "modal.passwordDetail.title": { "en": "Details", "fr": "Détail", "es": "Detalle" },

  "field.name": { "en": "Title", "fr": "Titre", "es": "Título" },
  "field.username": { "en": "Username", "fr": "Nom d'utilisateur", "es": "Usuario" },
  "field.website": { "en": "Site", "fr": "Site", "es": "Sitio" },
  "field.password": { "en": "Password", "fr": "Mot de passe", "es": "Contraseña" },
  "field.password.placeholder": { "en": "Your password", "fr": "Votre mot de passe", "es": "Tu contraseña" },
  "field.password.keep": { "en": "Leave empty to keep current password", "fr": "Laisser vide pour garder le mot de passe actuel", "es": "Dejar vacío para conservar la contraseña actual" },
  "field.notes": { "en": "Notes", "fr": "Notes", "es": "Notas" },
  "field.notes.placeholder": { "en": "Optional", "fr": "Optionnel", "es": "Opcional" },
  "field.category": { "en": "Category", "fr": "Catégorie", "es": "Categoría" },
  "field.createdAt": { "en": "Created", "fr": "Créé le", "es": "Creado el" },
  "field.updatedAt": { "en": "Updated", "fr": "Modifié le", "es": "Modificado el" },

  "placeholder.exampleName": { "en": "Ex: Gmail", "fr": "Ex : Gmail", "es": "Ej: Gmail" },
  "placeholder.exampleUsername": { "en": "Ex: john.doe", "fr": "Ex : jean.dupont", "es": "Ej: juan.perez" },
  "placeholder.website": { "en": "https://...", "fr": "https://...", "es": "https://..." },

  "category.uncategorized": { "en": "Uncategorized", "fr": "Sans catégorie", "es": "Sin categoría" },
  "category.add": { "en": "+ Add", "fr": "+ Ajouter", "es": "+ Añadir" },
  "category.new.placeholder": { "en": "New category", "fr": "Nouvelle catégorie", "es": "Nueva categoría" },
  "category.addButton": { "en": "Add", "fr": "Ajouter", "es": "Añadir" },
  "category.count.singular": { "en": "item", "fr": "élément", "es": "elemento" },
  "category.count.plural": { "en": "items", "fr": "éléments", "es": "elementos" },
  "category.editPlaceholder": {
    "en": "Edit category name",
    "fr": "Modifier le nom de la catégorie",
    "es": "Editar nombre de la categoría"
  },

  "actions.cancel": { "en": "Cancel", "fr": "Annuler", "es": "Cancelar" },
  "actions.add": { "en": "Add", "fr": "Ajouter", "es": "Añadir" },
  "actions.save": { "en": "Save", "fr": "Enregistrer", "es": "Guardar" },
  "actions.edit": { "en": "Edit", "fr": "Modifier", "es": "Editar" },
  "actions.validate": { "en": "Validate", "fr": "Valider", "es": "Validar" },

  "alert.error.title": { "en": "Error", "fr": "Erreur", "es": "Error" },

  "validation.requiredFields": { "en": "Required fields are missing (marked with *).", "fr": "Les champs marqués d'un * sont requis.", "es": "Los campos marcados con * son obligatorios." },
  "validation.categoryNameRequired": { "en": "Category name is required.", "fr": "Le nom de la catégorie est requis.", "es": "El nombre de la categoría es obligatorio." },
  "validation.field": { "en": "This field", "fr": "Ce champ", "es": "Este campo" },
  "validation.isRequired": { "en": "is required.", "fr": "est requis.", "es": "es obligatorio." },

  "accessibility.deleteCategory": { "en": "Delete category", "fr": "Supprimer la catégorie", "es": "Eliminar la categoría" },
  "accessibility.revealPassword": { "en": "Reveal password", "fr": "Révéler le mot de passe", "es": "Revelar contraseña" },

  "password.hidden": { "en": "••••••••", "fr": "••••••••", "es": "••••••••" },

  "exportAll.button": { "en": "Export all", "fr": "Exporter tout", "es": "Exportar todo" },
  "exportAll.dialogTitle": { "en": "Export all data", "fr": "Exporter toutes les données", "es": "Exportar todos los datos" },

  "exportByCategory.button": { "en": "Export selection", "fr": "Exporter sélection", "es": "Exportar selección" },
  "exportByCategory.dialogTitle": { "en": "Export selected categories", "fr": "Exporter catégories sélectionnées", "es": "Exportar categorías seleccionadas" },

  "alerts.fileAccess.error": { "en": "Unable to access file directory on this device.", "fr": "Impossible d'accéder au répertoire de fichiers sur cet appareil.", "es": "No es posible acceder al directorio de archivos en este dispositivo." },
  "alerts.export.error": { "en": "Export failed: {error}", "fr": "L'export a échoué : {error}", "es": "La exportación falló: {error}" },
  "alerts.export.selectedNoneTitle": { "en": "No category selected", "fr": "Aucune catégorie sélectionnée", "es": "Ninguna categoría seleccionada" },
  "alerts.export.selectedNoneMessage": { "en": "Select at least one category to export.", "fr": "Sélectionnez au moins une catégorie à exporter.", "es": "Selecciona al menos una categoría para exportar." },

  "import.button": { "en": "Import JSON", "fr": "Importer JSON", "es": "Importar JSON" },
  "alerts.import.noFileSelected": { "en": "No file selected.", "fr": "Aucun fichier sélectionné.", "es": "Ningún archivo seleccionado." },
  "alerts.import.cannotRetrieveFile": { "en": "Unable to read selected file.", "fr": "Impossible de récupérer le fichier sélectionné.", "es": "No se puede recuperar el archivo seleccionado." },
  "alerts.import.invalidJson": { "en": "Selected file is not valid JSON.", "fr": "Le fichier n'est pas un JSON valide.", "es": "El archivo no es un JSON válido." },
  "alerts.import.noData": { "en": "File contains no categories or passwords.", "fr": "Le fichier ne contient pas de catégories ni de mots de passe.", "es": "El archivo no contiene categorías ni contraseñas." },
  "alerts.import.nothingToImport": { "en": "Nothing imported — all items already exist.", "fr": "Aucune donnée importée : tout existe déjà.", "es": "Nada importado: todo ya existe." },
  "alerts.import.success": { "en": "Import successful", "fr": "Import réussi", "es": "Importación correcta" },
  "alerts.import.successDetails": { "en": "Imported: {cats} category(ies), {pwds} password(s).", "fr": "Importé : {cats} catégorie(s), {pwds} mot(s) de passe.", "es": "Importado: {cats} categoría(s), {pwds} contraseña(s)." },
  "alerts.import.applyError": { "en": "An error occurred applying the import: {error}", "fr": "Un problème est survenu pendant l'import : {error}", "es": "Ocurrió un error aplicando la importación: {error}" },
  "alerts.import.finalError": { "en": "Import failed: {error}", "fr": "Le fichier n'est pas un JSON valide ou une erreur est survenue : {error}", "es": "La importación falló: {error}" },

  "alerts.deleteCategory.forbiddenTitle": { "en": "Deletion forbidden", "fr": "Suppression impossible", "es": "Eliminación prohibida" },
  "alerts.deleteCategory.forbiddenMessage": { "en": "The 'Uncategorized' category cannot be deleted.", "fr": "La catégorie 'Sans catégorie' ne peut pas être supprimée.", "es": "La categoría 'Sin categoría' no se puede eliminar." },
  "alerts.deleteCategory.confirmTitle": { "en": "Delete category", "fr": "Supprimer la catégorie", "es": "Eliminar la categoría" },
  "alerts.deleteCategory.confirmMessage": { "en": "Deleting the category \"{name}\" will also remove {count} password(s). Confirm?", "fr": "Supprimer la catégorie \"{name}\" supprimera également {count} mot(s) de passe. Confirmez ?", "es": "Eliminar la categoría \"{name}\" eliminará {count} contraseña(s). ¿Confirmas?" },
  "alerts.deleteCategory.deletedTitle": { "en": "Deleted", "fr": "Supprimé", "es": "Eliminado" },
  "alerts.deleteCategory.deletedMessage": { "en": "Category \"{name}\" has been deleted.", "fr": "La catégorie \"{name}\" a été supprimée.", "es": "La categoría \"{name}\" ha sido eliminada." },
  "alerts.deleteCategory.undo": { "en": "Undo deletion", "fr": "Annuler la suppression", "es": "Deshacer eliminación" },
  "alerts.deleteCategory.errorMessage": { "en": "Unable to delete the category.", "fr": "Impossible de supprimer la catégorie.", "es": "No se pudo eliminar la categoría." },

  "alerts.deletePassword.confirmTitle": { "en": "Delete", "fr": "Supprimer", "es": "Eliminar" },
  "alerts.deletePassword.confirmMessage": { "en": "Do you really want to delete this password?", "fr": "Voulez-vous supprimer ce mot de passe ?", "es": "¿Desea eliminar esta contraseña?" },

  "question.hint.placeholder": {
    "en": "A hint to remind you of the answer",
    "fr": "Un indice pour vous rappeler la réponse",
    "es": "Una pista para recordarte la respuesta"
  },
  "question.hint.saved": { "en": "Hint saved", "fr": "Indice enregistré", "es": "Pista guardada" },

  "question.answer.placeholder": {
    "en": "Enter the answer to hash",
    "fr": "Entrez la réponse pour la hacher",
    "es": "Introduce la respuesta para hashearla"
  },
  "question.saveSuccess.title": { "en": "Success", "fr": "Succès", "es": "Éxito" },
  "question.saveSuccess.message": {
    "en": "Answer saved securely.",
    "fr": "Réponse enregistrée en toute sécurité.",
    "es": "Respuesta guardada de forma segura."
  },
  "question.saveError": {
    "en": "Unable to save the answer.",
    "fr": "Impossible d'enregistrer la réponse.",
    "es": "No se pudo guardar la respuesta."
  },

  "unlock.biometricPrompt": { "en": "Unlock", "fr": "Se déverrouiller", "es": "Desbloquear" },
  "unlock.authenticating": { "en": "Authenticating…", "fr": "Authentification en cours", "es": "Autenticando…" },
  "unlock.authenticatingHint": { "en": "Please follow the system biometric prompt.", "fr": "Veuillez suivre la demande biométrique du système.", "es": "Siga la solicitud biométrica del sistema." },

  "unlock.lockedTitle": { "en": "App locked", "fr": "Application verrouillée", "es": "Aplicación bloqueada" },
  "unlock.lockedHint": { "en": "Tap to try unlocking.", "fr": "Appuyez pour tenter de déverrouiller.", "es": "Pulse para intentar desbloquear." },

  "unlock.button.unlock": { "en": "Unlock", "fr": "Déverrouiller", "es": "Desbloquear" },
  "unlock.button.answer": { "en": "Answer", "fr": "Réponse", "es": "Respuesta" },

  "unlock.question.title": { "en": "Security question", "fr": "Question de sécurité", "es": "Pregunta de seguridad" },
  "unlock.question.hintFallback": { "en": "Answer your secret question", "fr": "Répondez à votre question secrète", "es": "Responda a su pregunta secreta" },

  "unlock.answer.placeholder": { "en": "Answer", "fr": "Réponse", "es": "Respuesta" },

  "unlock.error.emptyAnswer": { "en": "Answer is empty", "fr": "La réponse est vide", "es": "La respuesta está vacía" },
  "unlock.error.incorrectAnswer": { "en": "Incorrect answer", "fr": "Réponse incorrecte", "es": "Respuesta incorrecta" },

  "questions.1": {
    "en": "What was my first pet?",
    "fr": "Quel est mon premier animal de compagnie ?",
    "es": "¿Cuál fue mi primera mascota?"
  },
  "questions.2": {
    "en": "What is my favorite password?",
    "fr": "Quel est mon mot de passe préféré ?",
    "es": "¿Cuál es mi contraseña favorita?"
  },
  "questions.3": {
    "en": "What is my best friend's name?",
    "fr": "Quel est le nom de mon meilleur ami ?",
    "es": "¿Cómo se llama mi mejor amigo?"
  },
  "questions.4": {
    "en": "What city was I born in?",
    "fr": "Quelle est ma ville de naissance ?",
    "es": "¿En qué ciudad nací?"
  },
  "questions.5": {
    "en": "What was the model of my first car?",
    "fr": "Quel est le modèle de ma première voiture ?",
    "es": "¿Cuál fue el modelo de mi primer coche?"
  },

  "unlock.swipeToUnlock": {
    "en": "Swipe anywhere to unlock",
    "fr": "Faites glisser n'importe où pour déverrouiller",
    "es": "Desliza en cualquier lugar para desbloquear"
  },

  "search.placeholder": { "en": "Search categories or passwords", "fr": "Rechercher catégories ou mots de passe", "es": "Buscar categorías o contraseñas" },

  "password.copy.title": { "en": "Copied", "fr": "Copié", "es": "Copiado" },
  "password.copy.message": { "en": "Password copied to clipboard", "fr": "Mot de passe copié dans le presse-papiers", "es": "Contraseña copiada al portapapeles" },
  "password.copy.error": { "en": "Unable to copy password", "fr": "Impossible de copier le mot de passe", "es": "No se pudo copiar la contraseña" },
  "password.copy.hidden": { "en": "Password is hidden", "fr": "Le mot de passe est masqué", "es": "La contraseña está oculta" },
  "accessibility.copyPassword": { "en": "Copy password", "fr": "Copier le mot de passe", "es": "Copiar la contraseña" },
  "username.copy.title": { "en": "Copied", "fr": "Copié", "es": "Copiado" },
  "username.copy.message": { "en": "Username copied to clipboard", "fr": "Nom d'utilisateur copié dans le presse-papiers", "es": "Nombre de usuario copiado al portapapeles" },
  "username.copy.error": { "en": "Unable to copy username", "fr": "Impossible de copier le nom d'utilisateur", "es": "No se pudo copiar el nombre de usuario" },
  "username.copy.empty": { "en": "No username to copy", "fr": "Aucun nom d'utilisateur à copier", "es": "No hay nombre de usuario para copiar" },
  "accessibility.copyUsername": { "en": "Copy username", "fr": "Copier le nom d'utilisateur", "es": "Copiar nombre de usuario" },
  "website.open.error": { "en": "Unable to open link", "fr": "Impossible d'ouvrir le lien", "es": "No se pudo abrir el enlace" },

  "password.old.infoTitle": {
    "en": "Password flagged",
    "fr": "Mot de passe signalé",
    "es": "Contraseña señalada"
  },
  "password.old.infoMessage": {
    "en": "This password is older than your configured threshold and is flagged as 'old'. Consider changing it.",
    "fr": "Ce mot de passe est plus ancien que le seuil configuré et est marqué comme « ancien ». Pensez à le changer.",
    "es": "Esta contraseña es más antigua que el umbral configurado y está marcada como 'antigua'. Considere cambiarla."
  },
  "password.old.infoAccessibility": {
    "en": "Password flagged as old info",
    "fr": "Info mot de passe marqué ancien",
    "es": "Información contraseña marcada como antigua"
  },
  "category.label": { "en": "Category", "fr": "Catégorie", "es": "Categoría" },

  "passwordGenerator.title": { "en": "Password generator", "fr": "Générateur de mot de passe", "es": "Generador de contraseña" },
  "passwordGenerator.desc": { "en": "Create a random password and copy it to clipboard (not saved).", "fr": "Génère un mot de passe aléatoire et le copie (non enregistré).", "es": "Crea una contraseña aleatoria y la copia (no se guarda)." },
  "passwordGenerator.length.placeholder": { "en": "Length (e.g. 12)", "fr": "Longueur (ex. 12)", "es": "Longitud (ej. 12)" },
  "passwordGenerator.type.full": { "en": "Full (letters+digits+symbols)", "fr": "Complet (lettres+chiffres+symboles)", "es": "Completo (letras+números+símbolos)" },
  "passwordGenerator.type.digits": { "en": "Digits only", "fr": "Chiffres seulement", "es": "Solo dígitos" },
  "passwordGenerator.button.generate": { "en": "Generate", "fr": "Générer", "es": "Generar" },
  "passwordGenerator.button.copy": { "en": "Copy", "fr": "Copier", "es": "Copiar" },
  "passwordGenerator.copy.title": { "en": "Copied", "fr": "Copié", "es": "Copiado" },
  "passwordGenerator.copy.message": { "en": "Password copied to clipboard", "fr": "Mot de passe copié dans le presse-papiers", "es": "Contraseña copiada al portapapeles" },
  "passwordGenerator.copy.error": { "en": "Unable to copy password", "fr": "Impossible de copier le mot de passe", "es": "No se pudo copiar la contraseña" },
  "passwordGenerator.copy.noPassword": { "en": "No password to copy", "fr": "Aucun mot de passe à copier", "es": "No hay contraseña para copiar" },
  "title.copy.title": { "en": "Copied", "fr": "Copié", "es": "Copiado" },
  "title.copy.message": { "en": "Title copied to clipboard", "fr": "Titre copié dans le presse-papiers", "es": "Título copiado al portapapeles" },
  "title.copy.error": { "en": "Unable to copy title", "fr": "Impossible de copier le titre", "es": "No se pudo copiar el título" },
  "title.copy.empty": { "en": "No title to copy", "fr": "Aucun titre à copier", "es": "No hay título para copiar" },
  "accessibility.copyTitle": { "en": "Copy title", "fr": "Copier le titre", "es": "Copiar título" },
  "alerts.deletePassword.deletedTitle": { "en": "Deleted", "fr": "Supprimé", "es": "Eliminado" },
  "alerts.deletePassword.deletedMessage": {
    "en": "«{name}» deleted",
    "fr": "«{name}» supprimé",
    "es": "«{name}» eliminado"
  },
  "alerts.deletePassword.undo": { "en": "Undo", "fr": "Annuler", "es": "Deshacer" },
  "alerts.deletePassword.errorMessage": {
    "en": "Unable to delete password.",
    "fr": "Impossible de supprimer le mot de passe.",
    "es": "No se pudo eliminar la contraseña."
  },
  "accessibility.deletePassword": { "en": "Delete password", "fr": "Supprimer le mot de passe", "es": "Eliminar la contraseña" }
}